odoo/addons/website_sale_menu_partner_top_selling/README.rst
odoo/addons/website_sale_menu_partner_top_selling/__init__.py
odoo/addons/website_sale_menu_partner_top_selling/__manifest__.py
odoo/addons/website_sale_menu_partner_top_selling/controllers/__init__.py
odoo/addons/website_sale_menu_partner_top_selling/controllers/main.py
odoo/addons/website_sale_menu_partner_top_selling/i18n/ca.po
odoo/addons/website_sale_menu_partner_top_selling/i18n/es.po
odoo/addons/website_sale_menu_partner_top_selling/i18n/it.po
odoo/addons/website_sale_menu_partner_top_selling/i18n/website_sale_menu_partner_top_selling.pot
odoo/addons/website_sale_menu_partner_top_selling/models/__init__.py
odoo/addons/website_sale_menu_partner_top_selling/models/res_config_settings.py
odoo/addons/website_sale_menu_partner_top_selling/readme/CONFIGURE.md
odoo/addons/website_sale_menu_partner_top_selling/readme/CONTRIBUTORS.md
odoo/addons/website_sale_menu_partner_top_selling/readme/DESCRIPTION.md
odoo/addons/website_sale_menu_partner_top_selling/readme/USAGE.md
odoo/addons/website_sale_menu_partner_top_selling/static/description/icon.png
odoo/addons/website_sale_menu_partner_top_selling/static/description/index.html
odoo/addons/website_sale_menu_partner_top_selling/static/src/js/tours/website_sale_menu_top_user_selling_tour.esm.js
odoo/addons/website_sale_menu_partner_top_selling/tests/__init__.py
odoo/addons/website_sale_menu_partner_top_selling/tests/test_ui.py
odoo/addons/website_sale_menu_partner_top_selling/views/res_config_settings_views.xml
odoo/addons/website_sale_menu_partner_top_selling/views/templates.xml
odoo_addon_website_sale_menu_partner_top_selling-17.0.1.0.0.4.dist-info/METADATA
odoo_addon_website_sale_menu_partner_top_selling-17.0.1.0.0.4.dist-info/WHEEL
odoo_addon_website_sale_menu_partner_top_selling-17.0.1.0.0.4.dist-info/top_level.txt
odoo_addon_website_sale_menu_partner_top_selling-17.0.1.0.0.4.dist-info/RECORD
